{"cameraMode":{"drawMode":0,"name":"Shaded","section":"Shading Mode"},"sceneLighting":false,"audioPlay":false,"sceneViewState":{"showFog":true,"showMaterialUpdate":false,"showSkybox":false,"showFlares":true,"showImageEffects":true,"showParticleSystems":true,"showVisualEffectGraphs":true,"m_FxEnabled":true},"in2DMode":false,"pivot":{"x":-0.420505166053772,"y":1.8589372634887696,"z":-2.0374069213867189},"rotation":{"x":-0.005631756968796253,"y":0.9814183115959168,"z":-0.189570352435112,"w":-0.02915569394826889},"size":12.12435531616211,"orthographic":false}