{"cameraMode":{"drawMode":0,"name":"Shaded","section":"Shading Mode"},"sceneLighting":true,"audioPlay":false,"sceneViewState":{"showFog":true,"showMaterialUpdate":false,"showSkybox":false,"showFlares":true,"showImageEffects":true,"showParticleSystems":true,"showVisualEffectGraphs":true,"m_FxEnabled":true},"in2DMode":false,"pivot":{"x":7.238979339599609,"y":0.8170485496520996,"z":6.628886699676514},"rotation":{"x":-0.18248850107192994,"y":0.485441118478775,"z":-0.10438137501478195,"w":-0.848629355430603},"size":5.066205978393555,"orthographic":false}